CHANGES.txt
MANIFEST.in
README.txt
setup.cfg
setup.py
DeformAlchemy.egg-info/PKG-INFO
DeformAlchemy.egg-info/SOURCES.txt
DeformAlchemy.egg-info/dependency_links.txt
DeformAlchemy.egg-info/not-zip-safe
DeformAlchemy.egg-info/requires.txt
DeformAlchemy.egg-info/top_level.txt
deformalchemy/__init__.py
deformalchemy/form.py
deformalchemy/widget.py
tests/__init__.py
tests/models.py
tests/test_form.py