Metadata-Version: 1.1
Name: DeformAlchemy
Version: 0.1dev
Summary: DeformAlchemy
Home-page: UNKNOWN
Author: UNKNOWN
Author-email: UNKNOWN
License: MIT
Keywords: deform deform_boostrap twitter bootstrap colander colanderalchemy sqlalchemy
Platform: UNKNOWN
Classifier: Programming Language :: Python
Classifier: Framework :: Pyramid
Classifier: Topic :: Internet :: WWW/HTTP
Classifier: Topic :: Internet :: WWW/HTTP :: WSGI :: Application
